odoo/addons/template_content_swapper/README.rst
odoo/addons/template_content_swapper/__init__.py
odoo/addons/template_content_swapper/__manifest__.py
odoo/addons/template_content_swapper/i18n/it.po
odoo/addons/template_content_swapper/i18n/template_content_swapper.pot
odoo/addons/template_content_swapper/models/__init__.py
odoo/addons/template_content_swapper/models/ir_qweb.py
odoo/addons/template_content_swapper/models/template_content_mapping.py
odoo/addons/template_content_swapper/readme/CONFIGURE.md
odoo/addons/template_content_swapper/readme/CONTRIBUTORS.md
odoo/addons/template_content_swapper/readme/DESCRIPTION.md
odoo/addons/template_content_swapper/readme/USAGE.md
odoo/addons/template_content_swapper/security/ir.model.access.csv
odoo/addons/template_content_swapper/static/description/icon.png
odoo/addons/template_content_swapper/static/description/index.html
odoo/addons/template_content_swapper/static/img/login_after.png
odoo/addons/template_content_swapper/static/img/login_before.png
odoo/addons/template_content_swapper/static/img/mapping.png
odoo/addons/template_content_swapper/tests/__init__.py
odoo/addons/template_content_swapper/tests/test_template_content_swapper.py
odoo/addons/template_content_swapper/views/template_content_mapping_views.xml
odoo_addon_template_content_swapper-18.0.1.0.0.3.dist-info/METADATA
odoo_addon_template_content_swapper-18.0.1.0.0.3.dist-info/WHEEL
odoo_addon_template_content_swapper-18.0.1.0.0.3.dist-info/top_level.txt
odoo_addon_template_content_swapper-18.0.1.0.0.3.dist-info/RECORD
